MANIFEST.in
README.md
setup.py
django_ses_gateway/__init__.py
django_ses_gateway/receiving_mail.py
django_ses_gateway/sending_mail.py
django_ses_gateway.egg-info/PKG-INFO
django_ses_gateway.egg-info/SOURCES.txt
django_ses_gateway.egg-info/dependency_links.txt
django_ses_gateway.egg-info/requires.txt
django_ses_gateway.egg-info/top_level.txt